README.txt
setup.cfg
setup.py
docs/HISTORY.txt
zettwerk/__init__.py
zettwerk.users.egg-info/PKG-INFO
zettwerk.users.egg-info/SOURCES.txt
zettwerk.users.egg-info/dependency_links.txt
zettwerk.users.egg-info/entry_points.txt
zettwerk.users.egg-info/namespace_packages.txt
zettwerk.users.egg-info/not-zip-safe
zettwerk.users.egg-info/paster_plugins.txt
zettwerk.users.egg-info/requires.txt
zettwerk.users.egg-info/top_level.txt
zettwerk/users/__init__.py
zettwerk/users/configure.zcml
zettwerk/users/profiles.zcml
zettwerk/users/setuphandlers.py
zettwerk/users/Extensions/Install.py
zettwerk/users/browser/__init__.py
zettwerk/users/browser/configure.zcml
zettwerk/users/browser/userlistview.pt
zettwerk/users/browser/userlistview.py
zettwerk/users/browser/images/z.png
zettwerk/users/locales/zettwerk.users.pot
zettwerk/users/locales/de/LC_MESSAGES/zettwerk.users.po
zettwerk/users/profiles/default/controlpanel.xml
zettwerk/users/profiles/default/zettwerk.users.actionicons.txt
zettwerk/users/profiles/uninstall/controlpanel.xml
zettwerk/users/tests/__init__.py
zettwerk/users/tests/base.py
zettwerk/users/tests/test_userlistview.py