Metadata-Version: 1.0
Name: zettwerk.users
Version: 0.1
Summary: Additional user information for Plone
Home-page: http://svn.plone.org/svn/collective/zettwerk.users
Author: Christoph Glaubitz
Author-email: cg@zettwerk.com
License: GPL
Keywords: Zope CMF Plone Users
Platform: UNKNOWN
Classifier: Environment :: Web Environment
Classifier: Framework :: Plone
Classifier: Framework :: Zope2
Classifier: License :: OSI Approved :: GNU General Public License (GPL)
Classifier: Operating System :: OS Independent
Classifier: Programming Language :: Python
